quantalogic_pythonbox/__init__.py
quantalogic_pythonbox/assignment_visitors.py
quantalogic_pythonbox/async_builtins.py
quantalogic_pythonbox/async_function.py
quantalogic_pythonbox/async_generator.py
quantalogic_pythonbox/base_visitors.py
quantalogic_pythonbox/class_visitors.py
quantalogic_pythonbox/comprehension_visitors.py
quantalogic_pythonbox/context_visitors.py
quantalogic_pythonbox/control_flow_visitors.py
quantalogic_pythonbox/exception_visitors.py
quantalogic_pythonbox/exceptions.py
quantalogic_pythonbox/execution.py
quantalogic_pythonbox/function_base.py
quantalogic_pythonbox/function_utils.py
quantalogic_pythonbox/function_visitors.py
quantalogic_pythonbox/generator_wrapper.py
quantalogic_pythonbox/import_visitors.py
quantalogic_pythonbox/interpreter_core.py
quantalogic_pythonbox/lambda_function.py
quantalogic_pythonbox/literal_visitors.py
quantalogic_pythonbox/misc_visitors.py
quantalogic_pythonbox/mock_coroutine.py
quantalogic_pythonbox/operator_visitors.py
quantalogic_pythonbox/scope.py
quantalogic_pythonbox/slice_utils.py
quantalogic_pythonbox/visit_handlers.py
quantalogic_pythonbox-0.9.22.dist-info/LICENSE
quantalogic_pythonbox-0.9.22.dist-info/METADATA
quantalogic_pythonbox-0.9.22.dist-info/WHEEL
quantalogic_pythonbox-0.9.22.dist-info/RECORD
