Metadata-Version: 2.3
Name: quantalogic-pythonbox
Version: 0.9.22
Summary: A Python sandbox environment for implementing and testing CodeAct AI Agents.
License: Apache-2.0
Keywords: sandbox,python,codeact,agent,ast
Author: Raphael Mansuy
Author-email: raphael.mansuy@quantalogic.app
Requires-Python: >=3.9
Classifier: Development Status :: 4 - Beta
Classifier: Intended Audience :: Developers
Classifier: Intended Audience :: Science/Research
Classifier: License :: OSI Approved :: Apache Software License
Classifier: Operating System :: OS Independent
Classifier: Programming Language :: Python :: 3
Classifier: Programming Language :: Python :: 3.9
Classifier: Programming Language :: Python :: 3.10
Classifier: Programming Language :: Python :: 3.11
Classifier: Programming Language :: Python :: 3.12
Classifier: Topic :: Software Development :: Libraries :: Python Modules
Classifier: Topic :: Software Development :: Interpreters
Requires-Dist: loguru (>=0.7.0)
Requires-Dist: psutil (>=7.0.0)
Project-URL: Bug Tracker, https://github.com/quantalogic/quantalogic-pythonbox/issues
Project-URL: Documentation, https://github.com/quantalogic/quantalogic-pythonbox#readme
Project-URL: Homepage, https://github.com/quantalogic/quantalogic-pythonbox
Project-URL: Repository, https://github.com/quantalogic/quantalogic-pythonbox
